uss/__init__.py
uss/config.py
uss/evaluate.py
uss/inference.py
uss/losses.py
uss/parse_ontology.py
uss/train.py
uss/uss_inference.py
uss/utils.py
uss/callbacks/__init__.py
uss/callbacks/base.py
uss/callbacks/evaluate.py
uss/data/__init__.py
uss/data/anchor_segment_detectors.py
uss/data/anchor_segment_mixers.py
uss/data/datamodules.py
uss/data/datasets.py
uss/data/samplers.py
uss/dataset_creation/__init__.py
uss/dataset_creation/create_audioset_evaluation_meta.py
uss/models/__init__.py
uss/models/base.py
uss/models/film.py
uss/models/pl_modules.py
uss/models/query_nets.py
uss/models/resunet.py
uss/optimizers/__init__.py
uss/optimizers/lr_schedulers.py
uss-0.0.4.dist-info/LICENSE
uss-0.0.4.dist-info/METADATA
uss-0.0.4.dist-info/WHEEL
uss-0.0.4.dist-info/entry_points.txt
uss-0.0.4.dist-info/top_level.txt
uss-0.0.4.dist-info/RECORD
